CHANGES.txt
LICENSE.txt
MANIFEST.in
README.txt
setup.py
src/p01/__init__.py
src/p01.vocabulary.country.egg-info/PKG-INFO
src/p01.vocabulary.country.egg-info/SOURCES.txt
src/p01.vocabulary.country.egg-info/dependency_links.txt
src/p01.vocabulary.country.egg-info/namespace_packages.txt
src/p01.vocabulary.country.egg-info/not-zip-safe
src/p01.vocabulary.country.egg-info/requires.txt
src/p01.vocabulary.country.egg-info/top_level.txt
src/p01/vocabulary/__init__.py
src/p01/vocabulary/country/README.txt
src/p01/vocabulary/country/__init__.py
src/p01/vocabulary/country/configure.zcml
src/p01/vocabulary/country/country.py
src/p01/vocabulary/country/extract.py
src/p01/vocabulary/country/i18n.py
src/p01/vocabulary/country/locales.zcml
src/p01/vocabulary/country/mapping.py
src/p01/vocabulary/country/tests.py
src/p01/vocabulary/country/data/iso-3166-1-alpha-2.csv
src/p01/vocabulary/country/data/iso-3166-1-alpha-3.csv
src/p01/vocabulary/country/data/iso-3166-alpha-2.csv
src/p01/vocabulary/country/data/iso-3166-alpha-3.csv
src/p01/vocabulary/country/locales/af/LC_MESSAGES/iso3166.mo
src/p01/vocabulary/country/locales/af/LC_MESSAGES/iso3166.po
src/p01/vocabulary/country/locales/am/LC_MESSAGES/iso3166.mo
src/p01/vocabulary/country/locales/am/LC_MESSAGES/iso3166.po
src/p01/vocabulary/country/locales/ar/LC_MESSAGES/iso3166.mo
src/p01/vocabulary/country/locales/ar/LC_MESSAGES/iso3166.po
src/p01/vocabulary/country/locales/as/LC_MESSAGES/iso3166.mo
src/p01/vocabulary/country/locales/as/LC_MESSAGES/iso3166.po
src/p01/vocabulary/country/locales/ast/LC_MESSAGES/iso3166.mo
src/p01/vocabulary/country/locales/ast/LC_MESSAGES/iso3166.po
src/p01/vocabulary/country/locales/az/LC_MESSAGES/iso3166.mo
src/p01/vocabulary/country/locales/az/LC_MESSAGES/iso3166.po
src/p01/vocabulary/country/locales/be/LC_MESSAGES/iso3166.mo
src/p01/vocabulary/country/locales/be/LC_MESSAGES/iso3166.po
src/p01/vocabulary/country/locales/bg/LC_MESSAGES/iso3166.mo
src/p01/vocabulary/country/locales/bg/LC_MESSAGES/iso3166.po
src/p01/vocabulary/country/locales/bn/LC_MESSAGES/iso3166.mo
src/p01/vocabulary/country/locales/bn/LC_MESSAGES/iso3166.po
src/p01/vocabulary/country/locales/bn_IN/LC_MESSAGES/iso3166.mo
src/p01/vocabulary/country/locales/bn_IN/LC_MESSAGES/iso3166.po
src/p01/vocabulary/country/locales/br/LC_MESSAGES/iso3166.mo
