Metadata-Version: 2.1
Name: p01.vocabulary.country
Version: 0.6.0
Summary: ISO 3166-1 alpha-3 country codes vocabulary for Zope3
Home-page: http://pypi.python.org/pypi/p01.vocabulary.country
Author: Roger Ineichen, Projekt01 GmbH
Author-email: dev@projekt01.ch
License: ZPL 2.1
Keywords: zope3 z3c p01 vocabulary ISO 3166-1 alpha-3 country codes
Platform: UNKNOWN
Classifier: Development Status :: 4 - Beta
Classifier: Environment :: Web Environment
Classifier: Intended Audience :: Developers
Classifier: License :: OSI Approved :: Zope Public License
Classifier: Programming Language :: Python
Classifier: Natural Language :: English
Classifier: Operating System :: OS Independent
Classifier: Topic :: Internet :: WWW/HTTP
Classifier: Framework :: Zope3
Provides-Extra: test
Provides-Extra: extract
Provides-Extra: mapping
License-File: LICENSE.txt
